hellsicht/__init__.py
hellsicht/adapters/__init__.py
hellsicht/kernel/__init__.py
hellsicht/kernel/types/__init__.py
hellsicht/kernel/types/analysis.py
hellsicht/kernel/types/job.py
hellsicht/kernel/types/microkernel.py
hellsicht/kernel/types/progress.py
hellsicht/kernel/types/project.py
hellsicht/kernel/types/shape.py
hellsicht/servers/__init__.py
hellsicht/servers/external/__init__.py
hellsicht/servers/internal/__init__.py
hellsicht/servers/internal/analysis/__init__.py
hellsicht/servers/internal/analysis/patterns.py
hellsicht/servers/internal/preprocessing/__init__.py
hellsicht/servers/internal/preprocessing/tabular.py
hellsicht/servers/internal/types.py
hellsicht/types.py
hellsicht-0.1.1.dist-info/LICENSE
hellsicht-0.1.1.dist-info/METADATA
hellsicht-0.1.1.dist-info/WHEEL
hellsicht-0.1.1.dist-info/RECORD
